zns_logging/ZnsLogger.py
zns_logging/__init__.py
zns_logging/constant/HandlerConstant.py
zns_logging/constant/LoggerConstant.py
zns_logging/constant/__init__.py
zns_logging/utility/LogConsoleFormatter.py
zns_logging/utility/LogHandlerFactory.py
zns_logging/utility/__init__.py
zns_logging-1.1.5.dist-info/LICENSE
zns_logging-1.1.5.dist-info/METADATA
zns_logging-1.1.5.dist-info/WHEEL
zns_logging-1.1.5.dist-info/top_level.txt
zns_logging-1.1.5.dist-info/RECORD
