Metadata-Version: 2.1
Name: zns-logging
Version: 1.1.5
Summary: A simple and flexible logging library for Python
Home-page: https://github.com/Zennisch/zns_logging
Author: Zennisch
Author-email: zennisch@gmail.com
Requires-Python: >=3.10
License-File: LICENSE
Requires-Dist: colorama
